tnibs/__init__.py
tnibs/config.py
tnibs/data/__init__.py
tnibs/data/datasets/__init__.py
tnibs/data/datasets/datasets.py
tnibs/data/datasets/image.py
tnibs/data/modules/__init__.py
tnibs/data/modules/classifier.py
tnibs/data/modules/data.py
tnibs/data/modules/others.py
tnibs/data/utils/__init__.py
tnibs/data/utils/dataframes.py
tnibs/metric/__init__.py
tnibs/metric/metric.py
tnibs/metric/metrics.py
tnibs/metric/plot.py
tnibs/modules/__init__.py
tnibs/modules/modules.py
tnibs/train/__init__.py
tnibs/train/optim.py
tnibs/train/train.py
tnibs/train/utils.py
tnibs/user/__init__.py
tnibs/user/utils.py
tnibs/user/wandb.py
tnibs/utils/__init__.py
tnibs/utils/_utils.py
tnibs/utils/array.py
tnibs/utils/torch_utils.py
tnibs/utils/utils.py
torch_nibs-0.0.5.dist-info/METADATA
torch_nibs-0.0.5.dist-info/WHEEL
torch_nibs-0.0.5.dist-info/RECORD
