Metadata-Version: 2.4
Name: torch-nibs
Version: 0.0.5
Summary: A small framework for training and evaluating models in notebooks with pytorch
Author: manyhue
Classifier: License :: OSI Approved :: MIT License
Classifier: Operating System :: OS Independent
Classifier: Programming Language :: Python :: 3
Requires-Python: >=3.9
Requires-Dist: torcheval<0.0.8,>=0.0.7
